kroml/__init__.py
kroml/__main__.py
kroml/utils/__init__.py
kroml/utils/config_parser.py
kroml/utils/logger.py
kroml/utils/variable_context.py
kroml-0.0.2.dist-info/LICENSE
kroml-0.0.2.dist-info/METADATA
kroml-0.0.2.dist-info/WHEEL
kroml-0.0.2.dist-info/top_level.txt
kroml-0.0.2.dist-info/RECORD
