Metadata-Version: 2.1
Name: kroml
Version: 0.0.2
Summary: A framework for deploying ML projects.
Home-page: https://github.com/kroML/kroml
Author: kroML FW
Author-email: kroml.framework@gmail.com
License: UNKNOWN
Platform: UNKNOWN
Classifier: Development Status :: 2 - Pre-Alpha
Classifier: Programming Language :: Python :: 3
Classifier: License :: OSI Approved :: MIT License
Classifier: Operating System :: OS Independent
Requires-Python: >=3.6
